MANIFEST.in
README.md
setup.py
scripts/terraformGateway
tf_api_gateway/__init__.py
tf_api_gateway/tf_api_gateway.py
tf_api_gateway.egg-info/PKG-INFO
tf_api_gateway.egg-info/SOURCES.txt
tf_api_gateway.egg-info/dependency_links.txt
tf_api_gateway.egg-info/not-zip-safe
tf_api_gateway.egg-info/requires.txt
tf_api_gateway.egg-info/top_level.txt