Metadata-Version: 1.1
Name: tf-api-gateway
Version: 0.61
Summary: Wrapper for the Terraform Enterprise API
Home-page: http://github.com/PlethoraOfHate/tf_api_gateway
Author: Stephen Mercier
Author-email: stephen.mercier@gmail.com
License: Apache License 2.0
Download-URL: https://github.com/PlethoraOfHate/tf_api_gateway/archive/0.1.tar.gz
Keywords: terraform,atlas
Platform: UNKNOWN
Classifier: Development Status :: 3 - Alpha
Classifier: License :: OSI Approved :: Apache Software License
Classifier: Programming Language :: Python :: 3.5
Classifier: Topic :: Software Development :: Libraries :: Application Frameworks
